django_status_cats-0.1.1.dist-info/DESCRIPTION.rst
django_status_cats-0.1.1.dist-info/METADATA
django_status_cats-0.1.1.dist-info/RECORD
django_status_cats-0.1.1.dist-info/WHEEL
django_status_cats-0.1.1.dist-info/metadata.json
django_status_cats-0.1.1.dist-info/top_level.txt
status_cats/__init__.py
status_cats/constants.py
status_cats/middleware.py
status_cats/settings.py
status_cats/templates/status_cats/default.html
