Metadata-Version: 2.0
Name: django-status-cats
Version: 0.1.1
Summary: Django middleware for adding HTTP status cats to your responses 
Home-page: https://github.com/thatandromeda/django-status-cats
Author: Andromeda Yelton
Author-email: andromeda.yelton@gmail.com
License: CC0
Download-URL: https://github.com/thatandromeda/django-status-cats/tarball/0.1
Keywords: django middleware cats
Platform: UNKNOWN
Classifier: Framework :: Django
Classifier: License :: CC0 1.0 Universal (CC0 1.0) Public Domain Dedication
Classifier: Intended Audience :: Developers
Classifier: Development Status :: 3 - Alpha
Classifier: Environment :: Web Environment
Classifier: Programming Language :: Python :: 2
Requires-Dist: django
